Metadata-Version: 2.2
Name: NEWNAMEsalahaldin
Version: 0.1
Summary: Gaussian distributions
Dynamic: summary
